docs/.gitignore
docs/Makefile
docs/_static
docs/_templates
docs/conf.py
docs/index.rst
docs/make.bat
docs/ref/tkgen.rst
test/test_complex.py
test/test_opt.py
tkgen/__init__.py
tkgen/form.py
tkgen/tooltip.py
tkgen/assets/__init__.py
tkgen/assets/add.png
tkgen/assets/delete.png
tkgen/assets/edit.png
tkgen-0.2.4.dist-info/LICENSE
tkgen-0.2.4.dist-info/METADATA
tkgen-0.2.4.dist-info/WHEEL
tkgen-0.2.4.dist-info/top_level.txt
tkgen-0.2.4.dist-info/RECORD
