Metadata-Version: 2.1
Name: tkgen
Version: 0.2.4
Summary: A Tkinter form dialog generator.
Author-email: Théo Cavignac <theo.cavignac+dev@gmail.com>
License: BSD 3-Clause License
Project-URL: repository, https://git.sr.ht/~lattay/python-tkgen
Project-URL: documentation, https://tkgen.readthedocs.io
Classifier: License :: OSI Approved :: BSD License
Classifier: Programming Language :: Python :: 3
Requires-Python: >=3.7
License-File: LICENSE
Requires-Dist: pyskema (>=0.2)
